autotestify/__init__.py
autotestify/cli.py
autotestify/generator.py
autotestify-0.1.1.dist-info/METADATA
autotestify-0.1.1.dist-info/WHEEL
autotestify-0.1.1.dist-info/entry_points.txt
autotestify-0.1.1.dist-info/top_level.txt
autotestify-0.1.1.dist-info/RECORD
